isubsum.py
isubsum-0.1.dist-info/METADATA
isubsum-0.1.dist-info/WHEEL
isubsum-0.1.dist-info/entry_points.txt
isubsum-0.1.dist-info/top_level.txt
isubsum-0.1.dist-info/RECORD
