Metadata-Version: 2.1
Name: isubsum
Version: 0.1
Requires-Dist: Click
